wassup_broski/__init__.py
wassup_broski/huh.py
wassup_broski/programs.py
wassup_broski-0.0.4.dist-info/LICENCE
wassup_broski-0.0.4.dist-info/METADATA
wassup_broski-0.0.4.dist-info/WHEEL
wassup_broski-0.0.4.dist-info/top_level.txt
wassup_broski-0.0.4.dist-info/RECORD
