Metadata-Version: 2.1
Name: wassup_broski
Version: 0.0.4
Summary: Why do you want
Author-email: Unknown User <jakerebello2456@gmail.com>
Project-URL: Homepage, https://github.com/pypa/sampleproject
Project-URL: Issues, https://github.com/pypa/sampleproject/issues
Classifier: Programming Language :: Python :: 3
Classifier: License :: OSI Approved :: MIT License
Classifier: Operating System :: OS Independent
Requires-Python: >=3.8
License-File: LICENCE
